kmerhash/hasher.cpython-37m-x86_64-linux-gnu.so
kmerhash/hasher.pyx
kmerhash/hasher.c
kmerhash/hasher.pxd
kmerhash/.gitignore
kmerhash/__init__.py
kmerhash/__init__.pxd
kmerhash/tests/test1.py
kmerhash/tests/__init__.py
kmerhash-0.4.1.dist-info/METADATA
kmerhash-0.4.1.dist-info/LICENSE.md
kmerhash-0.4.1.dist-info/RECORD
kmerhash-0.4.1.dist-info/WHEEL
kmerhash-0.4.1.dist-info/top_level.txt
